README.md
setup.cfg
setup.py
dprep/__init__.py
dprep.egg-info/PKG-INFO
dprep.egg-info/SOURCES.txt
dprep.egg-info/dependency_links.txt
dprep.egg-info/requires.txt
dprep.egg-info/top_level.txt