Metadata-Version: 1.1
Name: dprep
Version: 0.1.13
Summary: Lightweight data preparation library for artificial intelligence and data science, built on top of pandas
Home-page: https://github.com/eykrehbein/dprep
Author: Eyk Rehbein
Author-email: eykrehbein@gmail.com
License: MIT
Download-URL: https://github.com/eykrehbein/dprep/archive/v_0.1.13.tar.gz
Keywords: data,data science,ai,artificial intelligence
Platform: UNKNOWN
Classifier: Development Status :: 3 - Alpha
Classifier: Intended Audience :: Developers
Classifier: Topic :: Software Development :: Build Tools
Classifier: License :: OSI Approved :: MIT License
Classifier: Programming Language :: Python :: 3
Classifier: Programming Language :: Python :: 3.4
Classifier: Programming Language :: Python :: 3.5
Classifier: Programming Language :: Python :: 3.6
Classifier: Programming Language :: Python :: 3.7
